Workbook
Name Aporte: Planilha1!$D$18:$D$18
Name Patrimonio: Planilha1!$D$21:$D$21
Name Qtd_anos: Planilha1!$D$19:$D$19
Name Rendimento_carteira: Planilha1!$D$14:$D$14
Name salario: Planilha1!$D$13:$D$13
Name sugestao_investimento: Planilha1!$D$15:$D$15
Name Taxa_mensal: Planilha1!$D$20:$D$20

Sheet Planilha1
C12: CONFIGURAÇÕES
C13: Salário | D13: 4200
C14: Rendimento da carteira | D14: 0.0089
C15: Sugestão de investimento | D15: =D13*30% -> 1260
C17: INVESTIMENTO MENSAL
C18: Quanto investir por mês? | D18: 1260
C19: Por quantos anos? | D19: 10
C20: Taxa de rendimento mensal? | D20: 0.01079
C21: Patrimônio acumulado? | D21: {=FV(Taxa_mensal,Qtd_anos*12,Aporte*-1)} -> 306538.11
C22: Dividendos mensais? | D22: {=Patrimonio*Rendimento_carteira} -> 2728.1892
C24: CENÁRIOS | E24: Dividendo
A25: 2 | C25: Quanto em 2 anos? | D25: =FV($D$20,$A25*12,$D$18*-1) -> 34306.81 | E25: =D25*$D$14 -> 305.33061
A26: 5 | C26: Quanto em 5 anos? | D26: =FV($D$20,$A26*12,$D$18*-1) -> 105558.91 | E26: =D26*$D$14 -> 939.47431
A27: 10 | C27: Quanto em 10 anos? | D27: =FV($D$20,$A27*12,$D$18*-1) -> 306538.11 | E27: =D27*$D$14 -> 2728.1892
A28: 30 | C28: Quanto em 30 anos? | D28: =FV($D$20,$A28*12,$D$18*-1) -> 5445933.8 | E28: =D28*$D$14 -> 48468.811
C30: PERFIL | D30: Conservador
C31: VALOR A SER INVESTIDO POR MÊS | D31: {=Aporte} -> 1260
C33: TIPO DE FII | D33: Percentual Sugerido | E33: Valores
C34: PAPEL | D34: =VLOOKUP($D$30&"-"&C34,Planilha2!$A:$D,4,FALSE) -> 0.3 | E34: =D34*$D$31 -> 378
C35: TIJOLO | D35: =VLOOKUP($D$30&"-"&C35,Planilha2!$A:$D,4,FALSE) -> 0.5 | E35: =D35*$D$31 -> 630
C36: HÍBRIDO | D36: =VLOOKUP($D$30&"-"&C36,Planilha2!$A:$D,4,FALSE) -> 0.1 | E36: =D36*$D$31 -> 126
C37: FOFs | D37: =VLOOKUP($D$30&"-"&C37,Planilha2!$A:$D,4,FALSE) -> 0.1 | E37: =D37*$D$31 -> 126
C38: DESENVOLVIMENTO | D38: =VLOOKUP($D$30&"-"&C38,Planilha2!$A:$D,4,FALSE) -> 0 | E38: =D38*$D$31 -> 0
C39: HOTELARIAS | D39: =VLOOKUP($D$30&"-"&C39,Planilha2!$A:$D,4,FALSE) -> 0 | E39: =D39*$D$31 -> 0

Sheet Planilha2
A2: Chave | B2: Perfil | C2: TIPO DE FII
A3: =B3&"-"&C3 -> Conservador-PAPEL | B3: Conservador | C3: PAPEL | D3: 0.3
A4: =B4&"-"&C4 -> Conservador-TIJOLO | B4: Conservador | C4: TIJOLO | D4: 0.5 | J4: %
A5: =B5&"-"&C5 -> Conservador-HÍBRIDO | B5: Conservador | C5: HÍBRIDO | D5: 0.1 | I5: Moderado-TIJOLO | J5: =VLOOKUP(I5,$A:$D,4,FALSE) -> 0.4
A6: =B6&"-"&C6 -> Conservador-FOFs | B6: Conservador | C6: FOFs | D6: 0.1
A7: =B7&"-"&C7 -> Conservador-DESENVOLVIMENTO | B7: Conservador | C7: DESENVOLVIMENTO | D7: 0
A8: =B8&"-"&C8 -> Conservador-HOTELARIAS | B8: Conservador | C8: HOTELARIAS | D8: 0
A9: =B9&"-"&C9 -> Moderado-PAPEL | B9: Moderado | C9: PAPEL | D9: 0.32
A10: =B10&"-"&C10 -> Moderado-TIJOLO | B10: Moderado | C10: TIJOLO | D10: 0.4
A11: =B11&"-"&C11 -> Moderado-HÍBRIDO | B11: Moderado | C11: HÍBRIDO | D11: 0.08
A12: =B12&"-"&C12 -> Moderado-FOFs | B12: Moderado | C12: FOFs | D12: 0.1
A13: =B13&"-"&C13 -> Moderado-DESENVOLVIMENTO | B13: Moderado | C13: DESENVOLVIMENTO | D13: 0.1
A14: =B14&"-"&C14 -> Moderado-HOTELARIAS | B14: Moderado | C14: HOTELARIAS | D14: 0.1
A15: =B15&"-"&C15 -> Agressivo-PAPEL | B15: Agressivo | C15: PAPEL | D15: 0.5
A16: =B16&"-"&C16 -> Agressivo-TIJOLO | B16: Agressivo | C16: TIJOLO | D16: 0.1
A17: =B17&"-"&C17 -> Agressivo-HÍBRIDO | B17: Agressivo | C17: HÍBRIDO | D17: 0.05
... A20: =B20&"-"&C20 -> Agressivo-HOTELARIAS | B20: Agressivo | C20: HOTELARIAS | D20: 0.1
